oculus/__init__.py
oculus_robotics-1.1.0.dist-info/METADATA
oculus_robotics-1.1.0.dist-info/WHEEL
oculus_robotics-1.1.0.dist-info/top_level.txt
oculus_robotics-1.1.0.dist-info/RECORD
