Metadata-Version: 2.4
Name: oculus-robotics
Version: 1.1.0
Summary: Real-time observability and safety for robotics simulations across all platforms
Author-email: Oculus Robotics <support@oculusrobotics.com>
License: Proprietary
Project-URL: Homepage, https://oculusrobotics.com
Project-URL: Documentation, https://docs.oculusrobotics.com
Project-URL: Repository, https://github.com/oculus-robotics/oculus-sdk
Project-URL: Issues, https://github.com/oculus-robotics/oculus-sdk/issues
Keywords: robotics,observability,isaac-sim,isaac-lab,ros2,mujoco,pybullet,gazebo,safety,prediction
Classifier: Development Status :: 4 - Beta
Classifier: Intended Audience :: Developers
Classifier: Intended Audience :: Science/Research
Classifier: Topic :: Scientific/Engineering :: Artificial Intelligence
Classifier: Programming Language :: Python :: 3
Classifier: Programming Language :: Python :: 3.8
Classifier: Programming Language :: Python :: 3.9
Classifier: Programming Language :: Python :: 3.10
Classifier: Programming Language :: Python :: 3.11
Requires-Python: >=3.8
Requires-Dist: python-socketio[client]>=5.10.0
Requires-Dist: numpy>=1.20.0
Requires-Dist: requests>=2.28.0
Requires-Dist: scikit-learn>=1.3.0
Requires-Dist: joblib>=1.3.0
Requires-Dist: pyyaml>=6.0
Requires-Dist: shap>=0.43.0
Provides-Extra: isaac-sim
Provides-Extra: isaac-lab
Provides-Extra: ros2
Requires-Dist: rclpy>=3.0; extra == "ros2"
Provides-Extra: mujoco
Requires-Dist: mujoco>=2.3.0; extra == "mujoco"
Provides-Extra: pybullet
Requires-Dist: pybullet>=3.2.0; extra == "pybullet"
Provides-Extra: gazebo
Requires-Dist: rclpy>=3.0; extra == "gazebo"
Provides-Extra: dev
Requires-Dist: pytest>=7.0; extra == "dev"
Requires-Dist: pytest-cov>=4.0; extra == "dev"
Requires-Dist: black>=22.0; extra == "dev"
Requires-Dist: mypy>=0.950; extra == "dev"
Requires-Dist: flake8>=5.0; extra == "dev"
Provides-Extra: all
Requires-Dist: rclpy>=3.0; extra == "all"
Requires-Dist: mujoco>=2.3.0; extra == "all"
Requires-Dist: pybullet>=3.2.0; extra == "all"
